[
    {
        "releaseTime": "Mar-16-23 05:19PM",
        "title": "Regional bank stability has major impact on spring building season: NAHB CEO",
        "publisher": " Yahoo Finance Video",
        "webUrl": "https://finance.yahoo.com/video/regional-bank-stability-major-impact-211951497.html",
        "company": "GS"
    },
    {
        "releaseTime": "Mar-16-23 03:35PM",
        "title": "First Republic Bank receives $30 billion in deposits from big banks",
        "publisher": " Yahoo Finance Video",
        "webUrl": "https://finance.yahoo.com/video/first-republic-bank-receives-30-193523357.html",
        "company": "GS"
    },
    {
        "releaseTime": "Mar-16-23 02:29PM",
        "title": "These are banking stocks you should buy right now: Analyst",
        "publisher": " Yahoo Finance Video",
        "webUrl": "https://finance.yahoo.com/video/banking-stocks-buy-now-analyst-182950533.html",
        "company": "GS"
    },
    {
        "releaseTime": "Mar-16-23 05:30AM",
        "title": "How Credit Suisse just unleashed a nightmare decision for the Fed and the ECB",
        "publisher": " Yahoo Finance",
        "webUrl": "https://finance.yahoo.com/news/how-credit-suisse-just-unleashed-a-nightmare-decision-for-the-fed-and-the-ecb-093016411.html",
        "company": "GS"
    },
    {
        "releaseTime": "Mar-15-23 08:00PM",
        "title": "How Goldmans Plan to Shore Up Silicon Valley Bank Crumbled",
        "publisher": " The Wall Street Journal",
        "webUrl": "https://finance.yahoo.com/m/195adf54-4a8e-36a3-bcba-44fec680975f/how-goldman%E2%80%99s-plan-to-shore.html",
        "company": "GS"
    },
    {
        "releaseTime": "Mar-15-23 02:47PM",
        "title": "Credit Suisse is a bank in search of a business, expert says",
        "publisher": " Yahoo Finance Video",
        "webUrl": "https://finance.yahoo.com/video/credit-suisse-bank-search-business-184723998.html",
        "company": "GS"
    },
    {
        "releaseTime": "Mar-15-23 02:18PM",
        "title": "Credit Suisse Credit Default Swap: What is it and how did it happen?",
        "publisher": " Yahoo Finance Video",
        "webUrl": "https://finance.yahoo.com/video/credit-suisse-credit-default-swap-181841513.html",
        "company": "GS"
    },
    {
        "releaseTime": "Mar-15-23 01:26PM",
        "title": "Banks under pressure: \"not the time to panic\"",
        "publisher": " Yahoo Finance Video",
        "webUrl": "https://finance.yahoo.com/video/banks-under-pressure-not-time-172652852.html",
        "company": "GS"
    },
    {
        "releaseTime": "Mar-15-23 07:16AM",
        "title": "SVB collapse leads to big paydays for short sellers",
        "publisher": " Yahoo Finance",
        "webUrl": "https://finance.yahoo.com/news/svb-collapse-silicon-valley-bank-short-sellers-111656437.html",
        "company": "GS"
    },
    {
        "releaseTime": "Mar-15-23 04:05AM",
        "title": "China Reports Economic Rebound But Warns of Risks To Recovery",
        "publisher": " Bloomberg",
        "webUrl": "https://finance.yahoo.com/news/china-economy-rebounds-covid-slump-022656482.html",
        "company": "GS"
    },
    {
        "releaseTime": "Mar-14-23 10:31PM",
        "title": "Analyst Report: The Goldman Sachs Group, Inc.",
        "publisher": " Morningstar Research",
        "webUrl": "https://finance.yahoo.com/m/5a1cf45d-8744-34eb-8fb0-0fd476158111/analyst-report%3A-the-goldman.html",
        "company": "GS"
    },
    {
        "releaseTime": "Mar-14-23 08:09PM",
        "title": "The roles Goldman Sachs played in the final days of Silicon Valley Bank",
        "publisher": " Yahoo Finance",
        "webUrl": "https://finance.yahoo.com/news/the-roles-goldman-sachs-played-in-the-final-days-of-silicon-valley-bank-000951274.html",
        "company": "GS"
    },
    {
        "releaseTime": "Mar-14-23 05:30PM",
        "title": "Silicon Valley Bank Creditors Form Group in Advance of Possible Bankruptcy",
        "publisher": " The Wall Street Journal",
        "webUrl": "https://finance.yahoo.com/m/c9f8a515-36aa-303f-82e5-cbeb25b59dc0/silicon-valley-bank-creditors.html",
        "company": "GS"
    },
    {
        "releaseTime": "Mar-14-23 10:47AM",
        "title": "The Companies Conducting Layoffs in 2023: Heres the List",
        "publisher": " The Wall Street Journal",
        "webUrl": "https://finance.yahoo.com/m/ef31b8d6-d5a6-36eb-b17c-de3d91997322/the-companies-conducting.html",
        "company": "GS"
    },
    {
        "releaseTime": "Mar-13-23 05:30AM",
        "title": "Silicon Valley Bank collapse  everything you need to know right now: Morning Brief",
        "publisher": " Yahoo Finance",
        "webUrl": "https://finance.yahoo.com/news/silicon-valley-bank-collapse--everything-you-need-to-know-right-now-morning-brief-093042703.html",
        "company": "GS"
    },
    {
        "releaseTime": "Mar-11-23 12:40PM",
        "title": "BBC Staff Revolts Over Suspension of Sports Commentator for Political Tweets",
        "publisher": " The Wall Street Journal",
        "webUrl": "https://finance.yahoo.com/m/43c91168-7a13-377d-b738-50fcb2a70432/bbc-staff-revolts-over.html",
        "company": "GS"
    },
    {
        "releaseTime": "Mar-10-23 01:49PM",
        "title": "Analyst Report: Goldman Sachs Group, Inc.",
        "publisher": " Argus Research",
        "webUrl": "https://finance.yahoo.com/m/6dc74c33-f184-3503-8f5d-ae2d27552e5a/analyst-report%3A-goldman-sachs.html",
        "company": "GS"
    },
    {
        "releaseTime": "Mar-10-23 01:34PM",
        "title": "Market Update: AAPL, BBY, ITGR, GS",
        "publisher": " Argus Research",
        "webUrl": "https://finance.yahoo.com/m/dc8483c4-1d0c-334f-b589-5a098a70e7ae/market-update%3A-aapl%2C-bby%2C.html",
        "company": "GS"
    },
    {
        "releaseTime": "Mar-10-23 01:26PM",
        "title": "Regulators close Silicon Valley Bank in largest failure since financial crisis",
        "publisher": " Yahoo Finance",
        "webUrl": "https://finance.yahoo.com/news/silicon-valley-bank-fdic-closed-largest-failure-financial-crisis-182643368.html",
        "company": "GS"
    },
    {
        "releaseTime": "Mar-09-23 03:25PM",
        "title": "Former Goldman Sachs Banker Sentenced to 10 Years in Prison for 1MDB Scandal",
        "publisher": " The Wall Street Journal",
        "webUrl": "https://finance.yahoo.com/m/215cbaf1-7b29-3632-baec-c61968b726d2/former-goldman-sachs-banker.html",
        "company": "GS"
    },
    {
        "releaseTime": "Mar-08-23 09:18AM",
        "title": "Goldman Sachs raises rate estimates following Fed Chair Powells testimony",
        "publisher": " Yahoo Finance Video",
        "webUrl": "https://finance.yahoo.com/video/goldman-sachs-raises-rate-estimates-141808443.html",
        "company": "GS"
    },
    {
        "releaseTime": "Mar-06-23 05:30PM",
        "title": "Apple stock boosted amid Goldman Sachs first Buy rating for iPhone maker in 6 years",
        "publisher": " Yahoo Finance Video",
        "webUrl": "https://finance.yahoo.com/video/apple-stock-boosted-amid-goldman-223049606.html",
        "company": "GS"
    },
    {
        "releaseTime": "Mar-06-23 04:23PM",
        "title": "Apple stock boosted amid Goldman Sachs first Buy rating for iPhone maker in 6 years",
        "publisher": " Yahoo Finance Video",
        "webUrl": "https://finance.yahoo.com/video/apple-stock-boosted-amid-goldman-212342477.html",
        "company": "GS"
    },
    {
        "releaseTime": "Mar-05-23 11:32PM",
        "title": "China Growth Plans Give Commodities Bulls Little to Run With",
        "publisher": " Bloomberg",
        "webUrl": "https://finance.yahoo.com/news/china-growth-plans-commodities-bulls-220000173.html",
        "company": "GS"
    },
    {
        "releaseTime": "Mar-04-23 12:00AM",
        "title": "Goldman Sachs Doesnt Want to Be Everyones Bank, but It Has to Be Someones",
        "publisher": " The Wall Street Journal",
        "webUrl": "https://finance.yahoo.com/m/fe9c2238-cbdb-3960-970a-2e7c1595bf7e/goldman-sachs-doesn%E2%80%99t-want-to.html",
        "company": "GS"
    },
    {
        "releaseTime": "Mar-03-23 04:17PM",
        "title": "Analyst Report: The Goldman Sachs Group, Inc.",
        "publisher": " Morningstar Research",
        "webUrl": "https://finance.yahoo.com/m/abc474ea-17af-344d-bcf7-925dcb84b9cb/analyst-report%3A-the-goldman.html",
        "company": "GS"
    },
    {
        "releaseTime": "Mar-03-23 03:41PM",
        "title": "These four cities could see double-digit home price drops: Goldman Sachs",
        "publisher": " Yahoo Finance",
        "webUrl": "https://finance.yahoo.com/news/these-four-cities-could-see-double-digit-home-price-drops-goldman-sachs-204112309.html",
        "company": "GS"
    },
    {
        "releaseTime": "Mar-02-23 08:00AM",
        "title": "Credit Agricole CIB, R. Seelaus & Co., and Siebert Williams Shank Join DirectBooks",
        "publisher": " PR Newswire",
        "webUrl": "https://finance.yahoo.com/news/credit-agricole-cib-r-seelaus-130000130.html",
        "company": "GS"
    },
    {
        "releaseTime": "Mar-01-23 12:10PM",
        "title": "Goldman Sachs tries to reset firm culture after three 'unusual' years",
        "publisher": " Yahoo Finance",
        "webUrl": "https://finance.yahoo.com/news/goldman-sachs-tries-to-reset-firm-culture-after-three-unusual-years-171038235.html",
        "company": "GS"
    },
    {
        "releaseTime": "Feb-28-23 05:52PM",
        "title": "Apollo in Talks to Buy Aerospace-Parts Maker Arconic",
        "publisher": " The Wall Street Journal",
        "webUrl": "https://finance.yahoo.com/m/e318add8-ea3c-32f3-ab29-abcdd146f276/apollo-in-talks-to-buy.html",
        "company": "GS"
    },
    {
        "releaseTime": "Feb-28-23 04:35PM",
        "title": "Goldman Considers Shrinking Its Consumer Business",
        "publisher": " The Wall Street Journal",
        "webUrl": "https://finance.yahoo.com/m/2efdd50d-1366-333d-8ac3-a6ca7da7897a/goldman-considers-shrinking.html",
        "company": "GS"
    },
    {
        "releaseTime": "Feb-28-23 03:29PM",
        "title": "Goldman Sachs Solomon addresses subsidiary guidance, growth outlook on investor day",
        "publisher": " Yahoo Finance Video",
        "webUrl": "https://finance.yahoo.com/video/goldman-sachs-solomon-addresses-subsidiary-202908400.html",
        "company": "GS"
    },
    {
        "releaseTime": "Feb-28-23 02:46PM",
        "title": "Goldman Sachs CEO: Soft landing odds improved, but inflation 'hampering confidence'",
        "publisher": " Yahoo Finance",
        "webUrl": "https://finance.yahoo.com/news/goldman-sachs-ceo-soft-landing-odds-improved-but-inflation-hampering-confidence-194601850.html",
        "company": "GS"
    },
    {
        "releaseTime": "Feb-28-23 02:41PM",
        "title": "Let Goldman Sachs Be Goldman Sachs",
        "publisher": " The Wall Street Journal",
        "webUrl": "https://finance.yahoo.com/m/738613d0-229f-3f5a-8598-c1d1217dfd84/let-goldman-sachs-be-goldman.html",
        "company": "GS"
    },
    {
        "releaseTime": "Feb-28-23 10:04AM",
        "title": "Goldman Sachs CEO David Solomon says Marcus 'lacked certain competitive advantage'",
        "publisher": " Yahoo Finance",
        "webUrl": "https://finance.yahoo.com/news/goldman-sachs-ceo-david-solomon-says-marcus-lacked-certain-competitive-advantage-150440695.html",
        "company": "GS"
    },
    {
        "releaseTime": "Feb-28-23 08:49AM",
        "title": "Goldman CEO Says Firm Is Considering Strategic Alternatives for Consumer Platforms",
        "publisher": " The Wall Street Journal",
        "webUrl": "https://finance.yahoo.com/m/2efdd50d-1366-333d-8ac3-a6ca7da7897a/goldman-ceo-says-firm-is.html",
        "company": "GS"
    },
    {
        "releaseTime": "Feb-27-23 03:45PM",
        "title": "Goldman Sachs CEO David Solomon to answer for 2023 outlook in Tuesdays investor day",
        "publisher": " Yahoo Finance Video",
        "webUrl": "https://finance.yahoo.com/video/goldman-sachs-ceo-david-solomon-204545118.html",
        "company": "GS"
    },
    {
        "releaseTime": "Feb-27-23 11:34AM",
        "title": "Goldman Sachs Investor Day: Investors eye execution plan, consumer finance unit",
        "publisher": " Yahoo Finance Video",
        "webUrl": "https://finance.yahoo.com/video/goldman-sachs-investor-day-investors-163417593.html",
        "company": "GS"
    },
    {
        "releaseTime": "Feb-27-23 10:00AM",
        "title": "The Fed Doesnt Care About Wall Street as Much as Wall Street Thinks",
        "publisher": " Bloomberg",
        "webUrl": "https://finance.yahoo.com/news/fed-doesn-t-care-wall-150000530.html",
        "company": "GS"
    },
    {
        "releaseTime": "Feb-27-23 08:57AM",
        "title": "German Bonds Dip to Multi-Year Lows as ECB Seen Hiking Into 2024",
        "publisher": " Bloomberg",
        "webUrl": "https://finance.yahoo.com/news/traders-bet-longer-ecb-rate-092725299.html",
        "company": "GS"
    },
    {
        "releaseTime": "Feb-27-23 06:29AM",
        "title": "Vitol Chief Sees Oil at $90-$100 in the Second Half of Year",
        "publisher": " Bloomberg",
        "webUrl": "https://finance.yahoo.com/news/vitol-chief-sees-oil-90-085701261.html",
        "company": "GS"
    },
    {
        "releaseTime": "Feb-24-23 08:00AM",
        "title": "'Everyone's a genius in a bull market' but this is simply a stock pickers' market: David Keller, CMT",
        "publisher": " Yahoo Finance Video",
        "webUrl": "https://finance.yahoo.com/video/everyones-genius-bull-market-simply-130001880.html",
        "company": "GS"
    },
    {
        "releaseTime": "Feb-23-23 06:17PM",
        "title": "Ozy Media, CEO Carlos Watson Charged With Fraud",
        "publisher": " The Wall Street Journal",
        "webUrl": "https://finance.yahoo.com/m/2d0e5535-0add-3737-a130-b3ce1b8c8939/ozy-media%2C-ceo-carlos-watson.html",
        "company": "GS"
    },
    {
        "releaseTime": "Feb-23-23 10:39AM",
        "title": "Ozy Media CEO Carlos Watson Arrested After a Former Executive Pleads Guilty to Fraud",
        "publisher": " The Wall Street Journal",
        "webUrl": "https://finance.yahoo.com/m/2d0e5535-0add-3737-a130-b3ce1b8c8939/ozy-media-ceo-carlos-watson.html",
        "company": "GS"
    },
    {
        "releaseTime": "Feb-22-23 01:47AM",
        "title": "New Zealand Raises Rate by Half-Point, Sees Further Tightening",
        "publisher": " Bloomberg",
        "webUrl": "https://finance.yahoo.com/news/zealand-delivers-half-point-rate-013056710.html",
        "company": "GS"
    },
    {
        "releaseTime": "Feb-21-23 05:22AM",
        "title": "Oil Eases in Rangebound Market as Fed and China Demand Face Off",
        "publisher": " Bloomberg",
        "webUrl": "https://finance.yahoo.com/news/oil-climbs-china-rebound-covid-233527802.html",
        "company": "GS"
    },
    {
        "releaseTime": "Feb-16-23 12:26PM",
        "title": "OPEC+ Deal Will Stay in Place All Year, Saudi Minister Says",
        "publisher": " Bloomberg",
        "webUrl": "https://finance.yahoo.com/news/opec-deal-remain-place-saudi-160331072.html",
        "company": "GS"
    },
    {
        "releaseTime": "Feb-16-23 09:57AM",
        "title": "Goldman Sachs Steps Back From Bidding for New Credit Card Programs",
        "publisher": " The Wall Street Journal",
        "webUrl": "https://finance.yahoo.com/m/980f0ddd-cf01-31b2-b26a-8afe518a8009/goldman-sachs-steps-back-from.html",
        "company": "GS"
    },
    {
        "releaseTime": "Feb-14-23 10:47AM",
        "title": "Goldman Sachs CEO Says Hes Focused on Tightening Expenses",
        "publisher": " The Wall Street Journal",
        "webUrl": "https://finance.yahoo.com/m/16b990cc-e26a-31f2-b303-9905f82332f9/goldman-sachs-ceo-says-he%E2%80%99s.html",
        "company": "GS"
    },
    {
        "releaseTime": "Feb-09-23 05:30AM",
        "title": "The Atlanta Billionaire Behind Goldmans Latest Consumer-Lending Push",
        "publisher": " The Wall Street Journal",
        "webUrl": "https://finance.yahoo.com/m/ffce430d-8c5e-3db2-854e-80adbfbec5b8/the-atlanta-billionaire.html",
        "company": "GS"
    },
    {
        "releaseTime": "Feb-06-23 07:00AM",
        "title": "Harvey Schwartz Named CEO of Carlyle and Member of the Board",
        "publisher": " GlobeNewswire",
        "webUrl": "https://finance.yahoo.com/news/harvey-schwartz-named-ceo-carlyle-120000432.html",
        "company": "GS"
    },
    {
        "releaseTime": "Feb-05-23 06:35PM",
        "title": "Carlyle to Name Banking Veteran Harvey Schwartz as CEO",
        "publisher": " The Wall Street Journal",
        "webUrl": "https://finance.yahoo.com/m/5095172a-3203-3fae-a7d1-859edce80599/carlyle-to-name-banking.html",
        "company": "GS"
    },
    {
        "releaseTime": "Feb-03-23 10:26AM",
        "title": "Goldman Sachs remains bullish on Meta stock",
        "publisher": " Yahoo Finance Video",
        "webUrl": "https://finance.yahoo.com/video/goldman-sachs-remains-bullish-meta-152642641.html",
        "company": "GS"
    },
    {
        "releaseTime": "Feb-02-23 08:57AM",
        "title": "Oil Steadies as Traders Weigh Fed Rate Outlook and China Demand",
        "publisher": " Bloomberg",
        "webUrl": "https://finance.yahoo.com/news/oil-edges-higher-traders-weigh-235821243.html",
        "company": "GS"
    },
    {
        "releaseTime": "Feb-02-23 08:15AM",
        "title": "The CEOs Taking Pay Cuts: Heres the List",
        "publisher": " The Wall Street Journal",
        "webUrl": "https://finance.yahoo.com/m/d9adeb8a-5b6f-3a19-a706-75e2ed9c0217/the-ceos-taking-pay-cuts%3A.html",
        "company": "GS"
    },
    {
        "releaseTime": "Jan-30-23 03:55PM",
        "title": "Goldman Sachs analysts rate Macys as one of the best positioned retail stocks",
        "publisher": " Yahoo Finance Video",
        "webUrl": "https://finance.yahoo.com/video/goldman-sachs-analysts-rate-macy-205501667.html",
        "company": "GS"
    },
    {
        "releaseTime": "Jan-27-23 12:38PM",
        "title": "Oil Flips to Loss As Key Technical Level Tests Bulls Resolve",
        "publisher": " Bloomberg",
        "webUrl": "https://finance.yahoo.com/news/oil-set-end-week-little-235023461.html",
        "company": "GS"
    },
    {
        "releaseTime": "Jan-27-23 11:36AM",
        "title": "Goldman Sachs Cut CEO David Solomons Pay to $25 Million in 2022",
        "publisher": " The Wall Street Journal",
        "webUrl": "https://finance.yahoo.com/m/1108da64-cfa9-3c31-b57e-57bfce5e14a0/goldman-sachs-cut-ceo-david.html",
        "company": "GS"
    },
    {
        "releaseTime": "Jan-25-23 12:00PM",
        "title": "Wall Street Trades in Asset-Backed Securities Face SEC Scrutiny for Conflicts",
        "publisher": " Bloomberg",
        "webUrl": "https://finance.yahoo.com/news/wall-street-trades-asset-backed-150000557.html",
        "company": "GS"
    },
    {
        "releaseTime": "Jan-25-23 03:25AM",
        "title": "Thailand Raises Key Rate to 1.5%, Signals More Tightening",
        "publisher": " Bloomberg",
        "webUrl": "https://finance.yahoo.com/news/thailand-raises-key-rate-quarter-070240865.html",
        "company": "GS"
    },
    {
        "releaseTime": "Jan-24-23 09:00AM",
        "title": "Crux Reports $75M in Bookings, Secures $50M in Funding to Accelerate Roadmap Development and Sales and Marketing",
        "publisher": " PR Newswire",
        "webUrl": "https://finance.yahoo.com/news/crux-reports-75m-bookings-secures-140000846.html",
        "company": "GS"
    },
    {
        "releaseTime": "Jan-23-23 01:30PM",
        "title": "Wall Street Is Minting Money as Revenue Rolls In",
        "publisher": " The Wall Street Journal",
        "webUrl": "https://finance.yahoo.com/m/0af29241-7070-35ba-92b0-235e7a3b1091/wall-street-is-minting-money.html",
        "company": "GS"
    },
    {
        "releaseTime": "Jan-20-23 05:55PM",
        "title": "Microsoft, Goldman Sachs, Netflix: Stocks That Defined the Week",
        "publisher": " The Wall Street Journal",
        "webUrl": "https://finance.yahoo.com/m/28073324-9d5d-3894-aa9e-c4492ffc94d0/microsoft%2C-goldman-sachs%2C.html",
        "company": "GS"
    },
    {
        "releaseTime": "Jan-20-23 04:36PM",
        "title": "Federal Reserve Probes Goldmans Consumer Business",
        "publisher": " The Wall Street Journal",
        "webUrl": "https://finance.yahoo.com/m/7a84cbed-a397-3cd9-9893-07863eddb85c/federal-reserve-probes.html",
        "company": "GS"
    },
    {
        "releaseTime": "Jan-20-23 04:35PM",
        "title": "Stocks moving this week: Netflix, Microsoft, Google, Goldman Sachs, Morgan Stanley, Tesla",
        "publisher": " Yahoo Finance Video",
        "webUrl": "https://finance.yahoo.com/video/stocks-moving-week-netflix-microsoft-213509514.html",
        "company": "GS"
    },
    {
        "releaseTime": "Jan-20-23 03:50PM",
        "title": "Fed probes Goldman Sachss consumer business unit",
        "publisher": " Yahoo Finance Video",
        "webUrl": "https://finance.yahoo.com/video/fed-probes-goldman-sachs-consumer-205017933.html",
        "company": "GS"
    },
    {
        "releaseTime": "Jan-20-23 12:16PM",
        "title": "Goldman Shares Drop After News of Consumer Bank Investigation",
        "publisher": " The Wall Street Journal",
        "webUrl": "https://finance.yahoo.com/m/2b8ea04c-79bc-3e57-b3d7-dc50adfacc42/goldman-shares-drop-after.html",
        "company": "GS"
    },
    {
        "releaseTime": "Jan-20-23 12:00PM",
        "title": "Stocks Move Higher Midday Friday",
        "publisher": " The Wall Street Journal",
        "webUrl": "https://finance.yahoo.com/m/573b6d4a-1870-35a4-b4ca-ef84c07a065d/stocks-move-higher-midday.html",
        "company": "GS"
    },
    {
        "releaseTime": "Jan-18-23 01:00PM",
        "title": "Goldman Sachs Asset Management and Lane Partners Announce Recapitalization of Southline Phase I with Beacon Capital Partners",
        "publisher": " PR Newswire",
        "webUrl": "https://finance.yahoo.com/news/goldman-sachs-asset-management-lane-180000910.html",
        "company": "GS"
    },
    {
        "releaseTime": "Jan-18-23 10:19AM",
        "title": "Goldman Sachs, Morgan Stanley cut jobs while other banks are still hiring",
        "publisher": " Yahoo Finance Video",
        "webUrl": "https://finance.yahoo.com/video/goldman-sachs-morgan-stanley-cut-151923873.html",
        "company": "GS"
    },
    {
        "releaseTime": "Jan-18-23 06:53AM",
        "title": "Analyst Report: Goldman Sachs Group, Inc.",
        "publisher": " Argus Research",
        "webUrl": "https://finance.yahoo.com/m/340cd8f9-ffb4-3995-b2af-a5790e43d514/analyst-report%3A-goldman-sachs.html",
        "company": "GS"
    },
    {
        "releaseTime": "Jan-18-23 06:38AM",
        "title": "Market Digest: CTSH, GS",
        "publisher": " Argus Research",
        "webUrl": "https://finance.yahoo.com/m/8a2e7157-0434-3740-867e-6d314089093e/market-digest%3A-ctsh%2C-gs.html",
        "company": "GS"
    },
    {
        "releaseTime": "Jan-17-23 04:55PM",
        "title": "The Problem at Goldman Sachs Isnt What You Think",
        "publisher": " The Wall Street Journal -6.44%",
        "webUrl": "https://finance.yahoo.com/m/f817ca33-6d90-3ac9-91f0-3dd44392c818/the-problem-at-goldman-sachs.html",
        "company": "GS"
    },
    {
        "releaseTime": "Jan-17-23 04:26PM",
        "title": "Stocks moving after the close: Goldman Sachs, Morgan Stanley, Alibaba, Roblox",
        "publisher": " Yahoo Finance Video",
        "webUrl": "https://finance.yahoo.com/video/stocks-moving-close-goldman-sachs-212612470.html",
        "company": "GS"
    },
    {
        "releaseTime": "Jan-17-23 04:24PM",
        "title": "Goldman Sachs, Morgan Stanley Profits Dented by Deal Slump",
        "publisher": " The Wall Street Journal",
        "webUrl": "https://finance.yahoo.com/m/d6a7081a-b84f-3f07-91e1-20ef4f59132f/goldman-sachs%2C-morgan-stanley.html",
        "company": "GS"
    },
    {
        "releaseTime": "Jan-17-23 03:56PM",
        "title": "Tesla stock rises following new analyst forecasts on price cuts",
        "publisher": " Yahoo Finance Video",
        "webUrl": "https://finance.yahoo.com/video/tesla-stock-rises-following-analyst-205635310.html",
        "company": "GS"
    },
    {
        "releaseTime": "Jan-17-23 03:45PM",
        "title": "As layoffs ripple across Wall Street, some banks stay in 'hiring mode'",
        "publisher": " Yahoo Finance",
        "webUrl": "https://finance.yahoo.com/news/wall-street-banks-q4-earnings-results-layoffs-economy-204526405.html",
        "company": "GS"
    },
    {
        "releaseTime": "Jan-17-23 03:32PM",
        "title": "Oil Edges Higher as Chinas Growth Outweighs Risk-Off Sentiment",
        "publisher": " Bloomberg",
        "webUrl": "https://finance.yahoo.com/news/oil-holds-decline-ahead-chinese-235757247.html",
        "company": "GS"
    },
    {
        "releaseTime": "Jan-17-23 03:23PM",
        "title": "Goldman Sachs stock falls amid earnings miss",
        "publisher": " Yahoo Finance Video",
        "webUrl": "https://finance.yahoo.com/video/goldman-sachs-stock-falls-amid-202319384.html",
        "company": "GS"
    },
    {
        "releaseTime": "Jan-17-23 01:16PM",
        "title": "Goldman Sachs Profit Plummets From Deal-Making Drought",
        "publisher": " The Wall Street Journal",
        "webUrl": "https://finance.yahoo.com/m/d6a7081a-b84f-3f07-91e1-20ef4f59132f/goldman-sachs-profit-plummets.html",
        "company": "GS"
    },
    {
        "releaseTime": "Jan-17-23 12:51PM",
        "title": "Goldman Sachs, Morgan Stanley Stocks Diverge as Indexes Waver",
        "publisher": " The Wall Street Journal",
        "webUrl": "https://finance.yahoo.com/m/74add04e-c9bd-349c-8537-08c9219a803e/goldman-sachs%2C-morgan-stanley.html",
        "company": "GS"
    },
    {
        "releaseTime": "Jan-17-23 11:16AM",
        "title": "Bank of America CEO: No mass layoff announcements are in the cards",
        "publisher": " Yahoo Finance",
        "webUrl": "https://finance.yahoo.com/news/bank-of-america-ceo-no-mass-layoff-announcements-161608280.html",
        "company": "GS"
    },
    {
        "releaseTime": "Jan-17-23 11:15AM",
        "title": "It's Earnings Day for Goldman SachsAnd CEO David Solomon's Birthday",
        "publisher": " The Wall Street Journal",
        "webUrl": "https://finance.yahoo.com/m/6cecfc94-4027-35ef-a0fc-22f4d67a296f/it%27s-earnings-day-for-goldman.html",
        "company": "GS"
    },
    {
        "releaseTime": "Jan-17-23 10:15AM",
        "title": "Bank earnings: Goldman Sachs and others see investment banking slowdown, layoffs",
        "publisher": " Yahoo Finance Video",
        "webUrl": "https://finance.yahoo.com/video/bank-earnings-goldman-sachs-others-151516408.html",
        "company": "GS"
    },
    {
        "releaseTime": "Jan-17-23 09:18AM",
        "title": "Earnings: Goldman Sachs posts profit miss, Morgan Stanley beats estimates",
        "publisher": " Yahoo Finance Video",
        "webUrl": "https://finance.yahoo.com/video/earnings-goldman-sachs-posts-profit-141800435.html",
        "company": "GS"
    },
    {
        "releaseTime": "Jan-17-23 07:39AM",
        "title": "Goldman Profit Plunges",
        "publisher": " The Wall Street Journal",
        "webUrl": "https://finance.yahoo.com/m/d73d28b2-94c6-3442-a824-f3aae26c515f/goldman-profit-plunges.html",
        "company": "GS"
    },
    {
        "releaseTime": "Jan-17-23 06:31AM",
        "title": "Goldman Sachs, Morgan Stanley to Post Earnings Shortly",
        "publisher": " The Wall Street Journal",
        "webUrl": "https://finance.yahoo.com/m/acf831e8-a19b-3ca2-8c41-1751a0d12793/goldman-sachs%2C-morgan-stanley.html",
        "company": "GS"
    },
    {
        "releaseTime": "Jan-13-23 05:33PM",
        "title": "Goldman Sachs Lost $3 Billion on Consumer Lending Push",
        "publisher": " The Wall Street Journal",
        "webUrl": "https://finance.yahoo.com/m/3f04009a-80ef-3a82-9858-1f63ec649642/goldman-sachs-lost-%243-billion.html",
        "company": "GS"
    },
    {
        "releaseTime": "Jan-13-23 04:45PM",
        "title": "S&P 500 Within a Whisker of 4,000 in Stock Rebound: Markets Wrap",
        "publisher": " Bloomberg",
        "webUrl": "https://finance.yahoo.com/news/asian-stocks-set-boost-easing-231025236.html",
        "company": "GS"
    },
    {
        "releaseTime": "Jan-13-23 10:24AM",
        "title": "Consumer sentiment index up as inflation eases, plus the top takeaways from bank earnings",
        "publisher": " Yahoo Finance Video",
        "webUrl": "https://finance.yahoo.com/video/bank-earnings-top-takeaways-lackluster-152455331.html",
        "company": "GS"
    },
    {
        "releaseTime": "Jan-13-23 09:18AM",
        "title": "Goldman Sachs, JPMorgan, Other Banks Sell Off in Early Trading",
        "publisher": " The Wall Street Journal",
        "webUrl": "https://finance.yahoo.com/m/dff80265-abb5-3f41-9107-1dec2fa2b948/goldman-sachs%2C-jpmorgan%2C.html",
        "company": "GS"
    },
    {
        "releaseTime": "Jan-13-23 07:32AM",
        "title": "Your Guide to Fourth-Quarter Bank Earnings",
        "publisher": " The Wall Street Journal",
        "webUrl": "https://finance.yahoo.com/m/c5405ba7-c9ba-3eed-8e85-b6a00e596e90/your-guide-to-fourth-quarter.html",
        "company": "GS"
    },
    {
        "releaseTime": "Jan-13-23 06:29AM",
        "title": "Goldman Sachs Lost $3 Billion on Consumer Lending Push",
        "publisher": " The Wall Street Journal",
        "webUrl": "https://finance.yahoo.com/m/ecd8c489-8191-3093-b7ea-07798f2b5e97/goldman-sachs-lost-%243-billion.html",
        "company": "GS"
    },
    {
        "releaseTime": "Jan-12-23 03:14PM",
        "title": "Oil Rises a Sixth Day as US Data Shows Inflation Moderating",
        "publisher": " Bloomberg",
        "webUrl": "https://finance.yahoo.com/news/oil-pushes-higher-sixth-session-000529209.html",
        "company": "GS"
    },
    {
        "releaseTime": "Jan-10-23 09:58AM",
        "title": "Corporate mentions of efficiency signal rise in cost-cutting efforts",
        "publisher": " Yahoo Finance Video",
        "webUrl": "https://finance.yahoo.com/video/corporate-mentions-efficiency-signal-rise-145848534.html",
        "company": "GS"
    },
    {
        "releaseTime": "Jan-09-23 03:48PM",
        "title": "Goldman Sachs to cut up to 3,200 jobs this week",
        "publisher": " Yahoo Finance Video",
        "webUrl": "https://finance.yahoo.com/video/goldman-sachs-cut-3-200-204848595.html",
        "company": "GS"
    },
    {
        "releaseTime": "Jan-09-23 11:19AM",
        "title": "The Debate Swirling Inside HR Departments: How to Lay Off Workers",
        "publisher": " The Wall Street Journal",
        "webUrl": "https://finance.yahoo.com/m/fc0a0a8a-6564-3f2f-8179-5a409a864c6e/the-debate-swirling-inside-hr.html",
        "company": "GS"
    },
    {
        "releaseTime": "Jan-09-23 09:18AM",
        "title": "Earnings: What to expect from big banks this week",
        "publisher": " Yahoo Finance Video",
        "webUrl": "https://finance.yahoo.com/video/earnings-expect-big-banks-week-141810694.html",
        "company": "GS"
    },
    {
        "releaseTime": "Jan-09-23 07:37AM",
        "title": "Goldman Sachs To Cut 3,200 Jobs Starting This Week",
        "publisher": " The Wall Street Journal",
        "webUrl": "https://finance.yahoo.com/m/a20e33c9-c359-3ae3-8ac4-8c954087cbbf/goldman-sachs-to-cut-3%2C200.html",
        "company": "GS"
    },
    {
        "releaseTime": "Jan-09-23 07:37AM",
        "title": "Goldman Sachs Plans To Cut 3,200 Jobs Starting This Week",
        "publisher": " The Wall Street Journal",
        "webUrl": "https://finance.yahoo.com/m/a20e33c9-c359-3ae3-8ac4-8c954087cbbf/goldman-sachs-plans-to-cut.html",
        "company": "GS"
    }
]